cobald/__about__.py
cobald/composite/__init__.py
cobald/composite/factory.py
cobald/composite/uniform.py
cobald/composite/weighted.py
cobald/controller/__init__.py
cobald/controller/linear.py
cobald/controller/relative_supply.py
cobald/controller/stepwise.py
cobald/controller/switch.py
cobald/daemon/__init__.py
cobald/daemon/__main__.py
cobald/daemon/debug.py
cobald/daemon/plugins.py
cobald/daemon/config/__init__.py
cobald/daemon/config/mapping.py
cobald/daemon/config/python.py
cobald/daemon/config/yaml.py
cobald/daemon/core/__init__.py
cobald/daemon/core/cli.py
cobald/daemon/core/config.py
cobald/daemon/core/logger.py
cobald/daemon/core/main.py
cobald/daemon/runners/__init__.py
cobald/daemon/runners/asyncio_runner.py
cobald/daemon/runners/base_runner.py
cobald/daemon/runners/guard.py
cobald/daemon/runners/meta_runner.py
cobald/daemon/runners/service.py
cobald/daemon/runners/thread_runner.py
cobald/daemon/runners/trio_runner.py
cobald/decorator/__init__.py
cobald/decorator/buffer.py
cobald/decorator/coarser.py
cobald/decorator/limiter.py
cobald/decorator/logger.py
cobald/decorator/standardiser.py
cobald/interfaces/__init__.py
cobald/interfaces/_composite.py
cobald/interfaces/_controller.py
cobald/interfaces/_partial.py
cobald/interfaces/_pool.py
cobald/interfaces/_proxy.py
cobald/monitor/__init__.py
cobald/monitor/format_json.py
cobald/monitor/format_line.py
cobald/utility/__init__.py
cobald/utility/primitives.py
cobald-0.14.0.dist-info/LICENSE
cobald-0.14.0.dist-info/METADATA
cobald-0.14.0.dist-info/WHEEL
cobald-0.14.0.dist-info/entry_points.txt
cobald-0.14.0.dist-info/top_level.txt
cobald-0.14.0.dist-info/RECORD
