Metadata-Version: 2.1
Name: cobald
Version: 0.14.0
Summary: COBalD - the Opportunistic Balancing Daemon
Home-page: https://github.com/MatterMiners/cobald
Author: Eileen Kuehn, Max Fischer
Author-email: matterminers@lists.kit.edu
License: MIT
Keywords: opportunistic scheduling scheduler demand feedback-loop cobald
Classifier: Intended Audience :: Developers
Classifier: Intended Audience :: Information Technology
Classifier: Intended Audience :: Science/Research
Classifier: Intended Audience :: System Administrators
Classifier: Topic :: Adaptive Technologies
Classifier: Topic :: Office/Business :: Scheduling
Classifier: Topic :: System :: Distributed Computing
Classifier: Programming Language :: Python :: 3
Classifier: Programming Language :: Python :: 3.8
Classifier: Programming Language :: Python :: 3.9
Classifier: Programming Language :: Python :: 3.10
Classifier: Programming Language :: Python :: 3.11
Requires-Python: >=3.8
License-File: LICENSE
Requires-Dist: pyyaml
Requires-Dist: trio (>=0.4.0)
Requires-Dist: entrypoints
Requires-Dist: toposort
Provides-Extra: contrib
Requires-Dist: flake8 ; extra == 'contrib'
Requires-Dist: flake8-bugbear ; extra == 'contrib'
Requires-Dist: pytest-cov ; extra == 'contrib'
Requires-Dist: pytest (>=4.3.0) ; extra == 'contrib'
Requires-Dist: pytest-timeout ; extra == 'contrib'
Requires-Dist: black ; (implementation_name == "cpython") and extra == 'contrib'
Provides-Extra: docs
Requires-Dist: sphinx ; extra == 'docs'
Requires-Dist: sphinx-rtd-theme ; extra == 'docs'
Provides-Extra: test
Requires-Dist: pytest (>=4.3.0) ; extra == 'test'
Requires-Dist: pytest-timeout ; extra == 'test'
